Metadata-Version: 2.1
Name: heptapod-import-roundup
Version: 0.1.1
Summary: Toolbox library for using the GitLab/Heptapod API for import use cases
Home-page: https://foss.heptapod.net/heptapod/heptapod-api-import
Author: Georges Racinet
Author-email: georges.racinet@octobus.net
License: GPL3+
Keywords: hg mercurial git heptapod gitlab
Platform: UNKNOWN
